{
  "currentPage": 1,
  "limit": 10,
  "results": [
    {
      "Bairro": "PRA\u00c7A DA BANDEIRA",
      "CEP": "36660000",
      "CNPJ": "19541931000125",
      "Cargo_Representante": "S\u00d3CIO ADMINISTRADOR",
      "Cidade": "Al\u00e9m Para\u00edba",
      "Complemento": null,
      "DDD": "32",
      "Data_Registro_ANS": "2015-05-19",
      "Endereco_eletronico": "contabilidade@cbnassessoria.com.br",
      "Fax": null,
      "Logradouro": "RUA CAPIT\u00c3O MEDEIROS DE REZENDE",
      "Modalidade": "Administradora de Benef\u00edcios",
      "Nome_Fantasia": null,
      "Numero": "274",
      "Razao_Social": "18 DE JULHO ADMINISTRADORA DE BENEF\u00cdCIOS LTDA",
      "Regiao_de_Comercializacao": "6",
      "Registro_ANS": "419761",
      "Representante": "LUIZ HENRIQUE MARENDINO GON\u00c7ALVES",
      "Telefone": "34624649",
      "UF": "MG"
    },
    {
      "Bairro": "VILA ROMANA",
      "CEP": "05049000",
      "CNPJ": "22869997000153",
      "Cargo_Representante": "S\u00d3CIO ADMINISTRADORA",
      "Cidade": "S\u00e3o Paulo",
      "Complemento": "SALA 126",
      "DDD": "11",
      "Data_Registro_ANS": "2019-06-13",
      "Endereco_eletronico": "labmarisol@gmail.com",
      "Fax": null,
      "Logradouro": "RUA CAT\u00c3O",
      "Modalidade": "Odontologia de Grupo",
      "Nome_Fantasia": null,
      "Numero": "128",
      "Razao_Social": "2B ODONTOLOGIA OPERADORA DE PLANOS ODONTOL\u00d3GICOS LTDA",
      "Regiao_de_Comercializacao": "4",
      "Registro_ANS": "421545",
      "Representante": "MARISOL BECHELLI",
      "Telefone": "34415852",
      "UF": "SP"
    },
    {
      "Bairro": "CENTRO",
      "CEP": "13010151",
      "CNPJ": "27452545000195",
      "Cargo_Representante": "REPRESENTANTE",
      "Cidade": "Campinas",
      "Complemento": "1\u00ba ANDAR",
      "DDD": "19",
      "Data_Registro_ANS": "2018-10-09",
      "Endereco_eletronico": "ans.plano@hospitalcare.com.br",
      "Fax": null,
      "Logradouro": "RUA: BERNARDINO DE CAMPOS",
      "Modalidade": "Medicina de Grupo",
      "Nome_Fantasia": null,
      "Numero": "230",
      "Razao_Social": "2CARE OPERADORA DE SA\u00daDE LTDA.",
      "Regiao_de_Comercializacao": "5",
      "Registro_ANS": "421421",
      "Representante": "RODRIGO PINHO RIBEIRO",
      "Telefone": "37901224",
      "UF": "SP"
    },
    {
      "Bairro": "JARDIM BONFIGLIOLI",
      "CEP": "13207280",
      "CNPJ": "41788751000100",
      "Cargo_Representante": "S\u00d3CIO ADMINISTRADOR",
      "Cidade": "Jundia\u00ed",
      "Complemento": "SALA 6",
      "DDD": "11",
      "Data_Registro_ANS": "2021-07-12",
      "Endereco_eletronico": "pietrorocchi37@gmail.com",
      "Fax": null,
      "Logradouro": "RUA IT\u00c1LIA",
      "Modalidade": "Administradora de Benef\u00edcios",
      "Nome_Fantasia": "3S ADMINISTRADORA DE BENEFICIOS",
      "Numero": "33",
      "Razao_Social": "3S ADMINISTRADORA DE BENEFICIOS LTDA",
      "Regiao_de_Comercializacao": "6",
      "Registro_ANS": "422908",
      "Representante": "ANAMELIA MONTEIRO GUERRA ROCCHI",
      "Telefone": "42263247",
      "UF": "SP"
    },
    {
      "Bairro": "SANTANA",
      "CEP": "02401000",
      "CNPJ": "13138885000131",
      "Cargo_Representante": "S\u00f3CIO-ADMINISTRADOR E REPRESEN",
      "Cidade": "S\u00e3o Paulo",
      "Complemento": "CONJUNTO 143 - SALA 01",
      "DDD": "11",
      "Data_Registro_ANS": "2011-05-05",
      "Endereco_eletronico": "diretoria@apssaude.com.br",
      "Fax": null,
      "Logradouro": "RUA VOLUNT\u00c1RIOS DA P\u00c1TRIA",
      "Modalidade": "Administradora de Benef\u00edcios",
      "Nome_Fantasia": "A.P.S. SA\u00daDE.",
      "Numero": "2525",
      "Razao_Social": "A.P.S. ADMINISTRADORA DE BENEF\u00cdCOS LTDA.",
      "Regiao_de_Comercializacao": "4",
      "Registro_ANS": "418030",
      "Representante": "PERC\u00cdVEL GAETA",
      "Telefone": "45223468",
      "UF": "SP"
    },
    {
      "Bairro": "SANTA EFIG\u00caNIA",
      "CEP": "30150281",
      "CNPJ": "17505793000101",
      "Cargo_Representante": "Diretor Presidente",
      "Cidade": "Belo Horizonte",
      "Complemento": "Subsolo, 2\u00ba andar e 3\u00ba andar",
      "DDD": "31",
      "Data_Registro_ANS": "1998-12-28",
      "Endereco_eletronico": "abertta.ans@arcelormittal.com.br",
      "Fax": "32484377",
      "Logradouro": "AV. BERNARDO MONTEIRO",
      "Modalidade": "Autogest\u00e3o",
      "Nome_Fantasia": "ABERTTA SA\u00daDE",
      "Numero": "831",
      "Razao_Social": "ABERTTA SA\u00daDE - ASSOCIA\u00c7\u00c3O BENEFICENTE DOS EMPREGADOS DA ARCELORMITTAL NO BRASIL",
      "Regiao_de_Comercializacao": "4",
      "Registro_ANS": "314668",
      "Representante": "RICARDO DUPIN LUSTOSA",
      "Telefone": "32484300",
      "UF": "MG"
    },
    {
      "Bairro": "BARRA DA TIJUCA",
      "CEP": "22775056",
      "CNPJ": "17687511000126",
      "Cargo_Representante": "ADMINISTRADOR",
      "Cidade": "Rio de Janeiro",
      "Complemento": "BLOCO 4, SALA 403",
      "DDD": null,
      "Data_Registro_ANS": "2014-11-13",
      "Endereco_eletronico": "contato@abplus.com.br",
      "Fax": null,
      "Logradouro": "AVENIDA JOS\u00c9 DA SILVA NETO",
      "Modalidade": "Administradora de Benef\u00edcios",
      "Nome_Fantasia": null,
      "Numero": "200",
      "Razao_Social": "ABPLUS ADMINISTRADORA DE BENEF\u00cdCIOS LTDA.",
      "Regiao_de_Comercializacao": "6",
      "Registro_ANS": "419621",
      "Representante": "ROBERTO CARLOS MACHADO RODRIGUES",
      "Telefone": null,
      "UF": "RJ"
    },
    {
      "Bairro": "HIGIENOPOLIS",
      "CEP": "01239030",
      "CNPJ": "56298884000167",
      "Cargo_Representante": "ADMINISTRADORA",
      "Cidade": "S\u00e3o Paulo",
      "Complemento": "SALA 13",
      "DDD": "11",
      "Data_Registro_ANS": "2025-01-06",
      "Endereco_eletronico": "dayanasantos@abrangesaude.com.br",
      "Fax": null,
      "Logradouro": "RUA CEL. JOS\u00c9 EUSEBIO",
      "Modalidade": "Administradora de Benef\u00edcios",
      "Nome_Fantasia": "ABRANGE SA\u00daDE",
      "Numero": "95.0",
      "Razao_Social": "ABRANGE ADMINISTRADORA DE BENEFICIOS LTDA.",
      "Regiao_de_Comercializacao": null,
      "Registro_ANS": "424242",
      "Representante": "DAYANA DOS SANTOSDE BRITO FLOR\u00caNCIO",
      "Telefone": "920554400",
      "UF": "SP"
    },
    {
      "Bairro": "CENTRO",
      "CEP": "20070020",
      "CNPJ": "10458298000131",
      "Cargo_Representante": "ADMINISTRADOR",
      "Cidade": "Rio de Janeiro",
      "Complemento": "SALA 2901",
      "DDD": "21",
      "Data_Registro_ANS": "2013-06-13",
      "Endereco_eletronico": "LEONARDO@UNIMEDICASAUDE.COM",
      "Fax": null,
      "Logradouro": "RUA BUENOS AIRES",
      "Modalidade": "Administradora de Benef\u00edcios",
      "Nome_Fantasia": "AD SALUTE",
      "Numero": "68",
      "Razao_Social": "AD SALUTE ADMINISTRADORA DE BENEF\u00cdCIOS LTDA",
      "Regiao_de_Comercializacao": "5",
      "Registro_ANS": "418901",
      "Representante": "JO\u00c3O CARMO DA SILVEIRA",
      "Telefone": "35531692",
      "UF": "RJ"
    },
    {
      "Bairro": "PINHEIROS",
      "CEP": "05420000",
      "CNPJ": "28315826000169",
      "Cargo_Representante": "S\u00f3cio Administrador",
      "Cidade": "S\u00e3o Paulo",
      "Complemento": "CJ 96",
      "DDD": "11",
      "Data_Registro_ANS": "2019-01-09",
      "Endereco_eletronico": "cristiane@admlife.com.br",
      "Fax": null,
      "Logradouro": "AVENIDA PEDROSO DE MORAIS",
      "Modalidade": "Administradora de Benef\u00edcios",
      "Nome_Fantasia": "ADM LIFE",
      "Numero": "272",
      "Razao_Social": "ADM LIFE - ADMINISTRADORA DE BENEF\u00cdCIOS LTDA.",
      "Regiao_de_Comercializacao": "4",
      "Registro_ANS": "421553",
      "Representante": "NELITO J\u00daNIOR DE ALMEIDA SILVA",
      "Telefone": "99475503",
      "UF": "SP"
    }
  ],
  "total": 1106,
  "totalPages": 111
}
